[
  {
    "name": "new",
    "path": "/new",
    "component": "/Users/leeseungho/Desktop/프로젝트/thlog/frontend/src/pages/new.vue",
    "chunkName": "pages/new"
  },
  {
    "name": "register",
    "path": "/register",
    "component": "/Users/leeseungho/Desktop/프로젝트/thlog/frontend/src/pages/register.vue",
    "chunkName": "pages/register"
  },
  {
    "name": "search",
    "path": "/search",
    "component": "/Users/leeseungho/Desktop/프로젝트/thlog/frontend/src/pages/search.vue",
    "chunkName": "pages/search"
  },
  {
    "name": "auth-github",
    "path": "/auth/github",
    "component": "/Users/leeseungho/Desktop/프로젝트/thlog/frontend/src/pages/auth/github.vue",
    "chunkName": "pages/auth/github"
  },
  {
    "name": "settings-profile",
    "path": "/settings/profile",
    "component": "/Users/leeseungho/Desktop/프로젝트/thlog/frontend/src/pages/settings/profile.vue",
    "chunkName": "pages/settings/profile"
  },
  {
    "path": "/",
    "component": "/Users/leeseungho/Desktop/프로젝트/thlog/frontend/src/pages/index.vue",
    "chunkName": "pages/index",
    "children": [
      {
        "name": "index",
        "path": "",
        "component": "/Users/leeseungho/Desktop/프로젝트/thlog/frontend/src/pages/index/index.vue",
        "chunkName": "pages/index/index"
      },
      {
        "name": "index-latest",
        "path": "latest",
        "component": "/Users/leeseungho/Desktop/프로젝트/thlog/frontend/src/pages/index/latest.vue",
        "chunkName": "pages/index/latest"
      }
    ]
  },
  {
    "path": "/:user",
    "component": "/Users/leeseungho/Desktop/프로젝트/thlog/frontend/src/pages/_user.vue",
    "chunkName": "pages/_user",
    "children": [
      {
        "name": "user",
        "path": "",
        "component": "/Users/leeseungho/Desktop/프로젝트/thlog/frontend/src/pages/_user/index.vue",
        "chunkName": "pages/_user/index"
      },
      {
        "name": "user-activities",
        "path": "activities",
        "component": "/Users/leeseungho/Desktop/프로젝트/thlog/frontend/src/pages/_user/activities.vue",
        "chunkName": "pages/_user/activities"
      },
      {
        "name": "user-feeds",
        "path": "feeds",
        "component": "/Users/leeseungho/Desktop/프로젝트/thlog/frontend/src/pages/_user/feeds.vue",
        "chunkName": "pages/_user/feeds"
      },
      {
        "name": "user-folders",
        "path": "folders",
        "component": "/Users/leeseungho/Desktop/프로젝트/thlog/frontend/src/pages/_user/folders.vue",
        "chunkName": "pages/_user/folders"
      },
      {
        "name": "user-follower",
        "path": "follower",
        "component": "/Users/leeseungho/Desktop/프로젝트/thlog/frontend/src/pages/_user/follower.vue",
        "chunkName": "pages/_user/follower"
      },
      {
        "name": "user-following",
        "path": "following",
        "component": "/Users/leeseungho/Desktop/프로젝트/thlog/frontend/src/pages/_user/following.vue",
        "chunkName": "pages/_user/following"
      },
      {
        "name": "user-thread-read",
        "path": "thread/:read?",
        "component": "/Users/leeseungho/Desktop/프로젝트/thlog/frontend/src/pages/_user/thread/_read.vue",
        "chunkName": "pages/_user/thread/_read"
      }
    ]
  }
]
